minchin/md_it/fancy_tasklists/__init__.py
minchin_md_it_fancy_tasklists-1.2.0.dist-info/METADATA
minchin_md_it_fancy_tasklists-1.2.0.dist-info/WHEEL
minchin_md_it_fancy_tasklists-1.2.0.dist-info/top_level.txt
minchin_md_it_fancy_tasklists-1.2.0.dist-info/RECORD
