Metadata-Version: 2.4
Name: minchin.md-it.fancy-tasklists
Version: 1.2.0
Summary: Fancy Tasklists, for Markdown-IT-py
Author-email: William Minchin <w_minchin@hotmail.com>
Maintainer-email: William Minchin <w_minchin@hotmail.com>
License: ISC
Project-URL: Bug Tracker, https://github.com/MinchinWeb/minchin.md-it.fancy-tasklists/issues
Project-URL: Repository, https://github.com/MinchinWeb/minchin.md-it.fancy-tasklists
Project-URL: Changelog, https://github.com/MinchinWeb/minchin.md-it.fancy-tasklists/blob/master/CHANGELOG.rst
Keywords: commonmark,markdown,plugin,tasklist,checkbox
Classifier: Development Status :: 5 - Production/Stable
Classifier: Environment :: Plugins
Classifier: Intended Audience :: End Users/Desktop
Classifier: Operating System :: OS Independent
Classifier: Topic :: Text Processing :: Markup :: Markdown
Classifier: Topic :: Software Development :: Libraries :: Python Modules
Requires-Dist: markdown-it-py
Provides-Extra: dev
Requires-Dist: pip-tools; extra == "dev"
Requires-Dist: minchin.releaser>=0.9.5; extra == "dev"
Requires-Dist: black; extra == "dev"
Requires-Dist: isort; extra == "dev"
